synthtool/__init__.py
synthtool/__main__.py
synthtool/_tracked_paths.py
synthtool/cache.py
synthtool/log.py
synthtool/metadata.py
synthtool/shell.py
synthtool/tmp.py
synthtool/transforms.py
synthtool/update_check.py
synthtool/gcp/__init__.py
synthtool/gcp/artman.py
synthtool/gcp/common.py
synthtool/gcp/discogapic_generator.py
synthtool/gcp/gapic_generator.py
synthtool/gcp/templates/README.txt
synthtool/gcp/templates/node_library/.eslintignore
synthtool/gcp/templates/node_library/.eslintrc.yml
synthtool/gcp/templates/node_library/.jsdoc.js
synthtool/gcp/templates/node_library/.nycrc
synthtool/gcp/templates/node_library/.prettierignore
synthtool/gcp/templates/node_library/.prettierrc
synthtool/gcp/templates/node_library/CODE_OF_CONDUCT.md
synthtool/gcp/templates/node_library/CONTRIBUTING.md
synthtool/gcp/templates/node_library/LICENSE
synthtool/gcp/templates/node_library/README.md
synthtool/gcp/templates/node_library/codecov.yaml
synthtool/gcp/templates/node_library/renovate.json
synthtool/gcp/templates/node_library/.github/ISSUE_TEMPLATE/bug_report.md
synthtool/gcp/templates/node_library/.github/ISSUE_TEMPLATE/feature_request.md
synthtool/gcp/templates/node_library/.github/ISSUE_TEMPLATE/support_request.md
synthtool/gcp/templates/node_library/.kokoro/common.cfg
synthtool/gcp/templates/node_library/.kokoro/docs.sh
synthtool/gcp/templates/node_library/.kokoro/lint.sh
synthtool/gcp/templates/node_library/.kokoro/publish.sh
synthtool/gcp/templates/node_library/.kokoro/samples-test.sh
synthtool/gcp/templates/node_library/.kokoro/system-test.sh
synthtool/gcp/templates/node_library/.kokoro/test.bat
synthtool/gcp/templates/node_library/.kokoro/test.sh
synthtool/gcp/templates/node_library/.kokoro/trampoline.sh
synthtool/gcp/templates/node_library/.kokoro/continuous/node10/common.cfg
synthtool/gcp/templates/node_library/.kokoro/continuous/node10/docs.cfg
synthtool/gcp/templates/node_library/.kokoro/continuous/node10/lint.cfg
gcp_synthtool-2019.5.2.dist-info/LICENSE
gcp_synthtool-2019.5.2.dist-info/METADATA
gcp_synthtool-2019.5.2.dist-info/WHEEL
gcp_synthtool-2019.5.2.dist-info/entry_points.txt
gcp_synthtool-2019.5.2.dist-info/top_level.txt
gcp_synthtool-2019.5.2.dist-info/RECORD
