Metadata-Version: 2.1
Name: gcp-synthtool
Version: 2019.5.2
Summary: UNKNOWN
Home-page: UNKNOWN
Author: Google LLC
Author-email: theaflowers@google.com
License: Apache 2.0
Platform: Posix; MacOS X; Windows
Classifier: Development Status :: 3 - Alpha
Classifier: Intended Audience :: Developers
Classifier: License :: OSI Approved :: Apache Software License
Classifier: Programming Language :: Python
Classifier: Programming Language :: Python :: 3.6
Classifier: Operating System :: OS Independent
Classifier: Topic :: Internet
Requires-Dist: click
Requires-Dist: colorlog
Requires-Dist: jinja2
Requires-Dist: packaging
Requires-Dist: PyYAML
Requires-Dist: requests
Requires-Dist: protobuf
